{
    "name": "Nike HyperTrack",
    "description": "A high-performance trail shoe built for rugged terrain. Highlights include an all-black upper with reflective accents, reinforced overlays, and a rugged sole with deep treads for maximum grip.",
    "image": "https://raw.githubusercontent.com/muriloandrade/CredblyNFT/refs/heads/master/public/NFTs/Nike/hypertrack.jpeg",
    "type": "image/jpeg",
    "files": [
        {
            "uri": "https://raw.githubusercontent.com/muriloandrade/CredblyNFT/refs/heads/master/public/NFTs/Nike/hypertrack.jpeg",
            "is_default_file": true,
            "type": "image/jpeg"
        }
    ]
}